{
  "annotations": {
    "list": [
      {
        "builtIn": 1,
        "datasource": "-- Grafana --",
        "enable": true,
        "hide": true,
        "iconColor": "rgba(0, 211, 255, 1)",
        "name": "Annotations & Alerts",
        "type": "dashboard"
      }
    ]
  },
  "editable": true,
  "gnetId": null,
  "graphTooltip": 0,
  "id": 1,
  "links": [],
  "panels": [
    {
      "datasource": null,
      "fieldConfig": {
        "defaults": {
          "custom": {},
          "mappings": [],
          "thresholds": {
            "mode": "absolute",
            "steps": [
              {
                "color": "green",
                "value": null
              },
              {
                "color": "red",
                "value": 80
              }
            ]
          }
        },
        "overrides": []
      },
      "gridPos": {
        "h": 2,
        "w": 5,
        "x": 0,
        "y": 0
      },
      "id": 4,
      "options": {
        "colorMode": "value",
        "graphMode": "area",
        "justifyMode": "auto",
        "orientation": "auto",
        "reduceOptions": {
          "calcs": [
            "last"
          ],
          "fields": "/.*/",
          "values": false
        },
        "textMode": "value"
      },
      "pluginVersion": "7.3.3",
      "targets": [
        {
          "format": "table",
          "group": [],
          "metricColumn": "none",
          "rawQuery": true,
          "rawSql": "SELECT ts AS time, j->'value' AS state \nFROM situation_history_v1  CROSS JOIN lateral json_array_elements ( metadatas ) AS j WHERE j->>'key' = 'state_perpignan' \nAND $__timeFilter(ts)",
          "refId": "A",
          "select": [
            [
              {
                "params": [
                  "value"
                ],
                "type": "column"
              }
            ]
          ],
          "timeColumn": "time",
          "where": [
            {
              "name": "$__timeFilter",
              "params": [],
              "type": "macro"
            }
          ]
        }
      ],
      "timeFrom": null,
      "timeShift": null,
      "title": "Current Wind State - Perpignan",
      "type": "stat"
    },
    {
      "datasource": null,
      "fieldConfig": {
        "defaults": {
          "custom": {},
          "mappings": [],
          "thresholds": {
            "mode": "absolute",
            "steps": [
              {
                "color": "green",
                "value": null
              },
              {
                "color": "red",
                "value": 80
              }
            ]
          }
        },
        "overrides": []
      },
      "gridPos": {
        "h": 2,
        "w": 5,
        "x": 5,
        "y": 0
      },
      "id": 6,
      "options": {
        "colorMode": "value",
        "graphMode": "area",
        "justifyMode": "auto",
        "orientation": "auto",
        "reduceOptions": {
          "calcs": [
            "last"
          ],
          "fields": "/.*/",
          "values": false
        },
        "textMode": "value"
      },
      "pluginVersion": "7.3.3",
      "targets": [
        {
          "format": "table",
          "group": [],
          "metricColumn": "none",
          "rawQuery": true,
          "rawSql": "SELECT ts AS time, j->'value' AS state \nFROM situation_history_v1  CROSS JOIN lateral json_array_elements ( metadatas ) AS j WHERE j->>'key' = 'state_montpellier' \nAND $__timeFilter(ts)",
          "refId": "A",
          "select": [
            [
              {
                "params": [
                  "value"
                ],
                "type": "column"
              }
            ]
          ],
          "timeColumn": "time",
          "where": [
            {
              "name": "$__timeFilter",
              "params": [],
              "type": "macro"
            }
          ]
        }
      ],
      "timeFrom": null,
      "timeShift": null,
      "title": "Current Wind State - Montpellier",
      "type": "stat"
    },
    {
      "datasource": null,
      "fieldConfig": {
        "defaults": {
          "custom": {},
          "mappings": [],
          "thresholds": {
            "mode": "absolute",
            "steps": [
              {
                "color": "green",
                "value": null
              },
              {
                "color": "red",
                "value": 80
              }
            ]
          }
        },
        "overrides": []
      },
      "gridPos": {
        "h": 2,
        "w": 5,
        "x": 10,
        "y": 0
      },
      "id": 5,
      "options": {
        "colorMode": "value",
        "graphMode": "area",
        "justifyMode": "auto",
        "orientation": "auto",
        "reduceOptions": {
          "calcs": [
            "last"
          ],
          "fields": "/.*/",
          "values": false
        },
        "textMode": "value"
      },
      "pluginVersion": "7.3.3",
      "targets": [
        {
          "format": "table",
          "group": [],
          "metricColumn": "none",
          "rawQuery": true,
          "rawSql": "SELECT ts AS time, j->'value' AS state \nFROM situation_history_v1  CROSS JOIN lateral json_array_elements ( metadatas ) AS j WHERE j->>'key' = 'state_narbonne' \nAND $__timeFilter(ts)",
          "refId": "A",
          "select": [
            [
              {
                "params": [
                  "value"
                ],
                "type": "column"
              }
            ]
          ],
          "timeColumn": "time",
          "where": [
            {
              "name": "$__timeFilter",
              "params": [],
              "type": "macro"
            }
          ]
        }
      ],
      "timeFrom": null,
      "timeShift": null,
      "title": "Current Wind State - Narbonne",
      "type": "stat"
    },
    {
      "datasource": null,
      "fieldConfig": {
        "defaults": {
          "custom": {},
          "mappings": [],
          "thresholds": {
            "mode": "absolute",
            "steps": [
              {
                "color": "green",
                "value": null
              },
              {
                "color": "red",
                "value": 80
              }
            ]
          }
        },
        "overrides": []
      },
      "gridPos": {
        "h": 2,
        "w": 5,
        "x": 15,
        "y": 0
      },
      "id": 7,
      "options": {
        "colorMode": "value",
        "graphMode": "area",
        "justifyMode": "auto",
        "orientation": "auto",
        "reduceOptions": {
          "calcs": [
            "last"
          ],
          "fields": "/.*/",
          "values": false
        },
        "textMode": "value"
      },
      "pluginVersion": "7.3.3",
      "targets": [
        {
          "format": "table",
          "group": [],
          "metricColumn": "none",
          "rawQuery": true,
          "rawSql": "SELECT ts AS time, j->'value' AS state \nFROM situation_history_v1  CROSS JOIN lateral json_array_elements ( metadatas ) AS j WHERE j->>'key' = 'state_avg' \nAND $__timeFilter(ts)",
          "refId": "A",
          "select": [
            [
              {
                "params": [
                  "value"
                ],
                "type": "column"
              }
            ]
          ],
          "timeColumn": "time",
          "where": [
            {
              "name": "$__timeFilter",
              "params": [],
              "type": "macro"
            }
          ]
        }
      ],
      "timeFrom": null,
      "timeShift": null,
      "title": "Current Wind State - avg",
      "type": "stat"
    },
    {
      "aliasColors": {},
      "bars": false,
      "dashLength": 10,
      "dashes": false,
      "datasource": "PostgreSQL",
      "fieldConfig": {
        "defaults": {
          "custom": {}
        },
        "overrides": []
      },
      "fill": 1,
      "fillGradient": 0,
      "gridPos": {
        "h": 10,
        "w": 20,
        "x": 0,
        "y": 2
      },
      "hiddenSeries": false,
      "id": 2,
      "legend": {
        "avg": false,
        "current": false,
        "max": false,
        "min": false,
        "show": true,
        "total": false,
        "values": false
      },
      "lines": true,
      "linewidth": 1,
      "nullPointMode": "null",
      "options": {
        "alertThreshold": true
      },
      "percentage": false,
      "pluginVersion": "7.3.3",
      "pointradius": 2,
      "points": false,
      "renderer": "flot",
      "seriesOverrides": [],
      "spaceLength": 10,
      "stack": false,
      "steppedLine": false,
      "targets": [
        {
          "format": "time_series",
          "group": [],
          "metricColumn": "none",
          "rawQuery": true,
          "rawSql": "SELECT sh.ts as time, \n(SELECT (result->'aggs'->'value'->'value')::INTEGER FROM fact_history_v1 WHERE id = 4 AND ts = (sh.facts_ids->>'4')::timestamptZ) as speed_avg \nFROM situation_history_v1 as sh\nWHERE\n  $__timeFilter(sh.ts)\nORDER BY sh.ts",
          "refId": "A",
          "select": [
            [
              {
                "params": [
                  "id"
                ],
                "type": "column"
              }
            ],
            [
              {
                "params": [
                  "situation_instance_id"
                ],
                "type": "column"
              }
            ]
          ],
          "table": "situation_history_v1",
          "timeColumn": "ts",
          "timeColumnType": "timestamptz",
          "where": [
            {
              "name": "$__timeFilter",
              "params": [],
              "type": "macro"
            }
          ]
        },
        {
          "format": "time_series",
          "group": [],
          "metricColumn": "none",
          "rawQuery": true,
          "rawSql": "SELECT sh.ts as time, (SELECT (result->'aggs'->'speed'->'value')::INTEGER FROM fact_history_v1 WHERE id = 1 AND ts = (sh.facts_ids->>'1')::timestamptZ) as speed_perpignan FROM situation_history_v1 as sh\nWHERE\n  $__timeFilter(sh.ts)\nORDER BY sh.ts",
          "refId": "B",
          "select": [
            [
              {
                "params": [
                  "value"
                ],
                "type": "column"
              }
            ]
          ],
          "timeColumn": "time",
          "where": [
            {
              "name": "$__timeFilter",
              "params": [],
              "type": "macro"
            }
          ]
        },
        {
          "format": "time_series",
          "group": [],
          "metricColumn": "none",
          "rawQuery": true,
          "rawSql": "SELECT sh.ts as time, (SELECT (result->'aggs'->'speed'->'value')::INTEGER FROM fact_history_v1 WHERE id = 2 AND ts = (sh.facts_ids->>'2')::timestamptZ) as sped_narbonne FROM situation_history_v1 as sh\nWHERE\n  $__timeFilter(sh.ts)\nORDER BY sh.ts",
          "refId": "C",
          "select": [
            [
              {
                "params": [
                  "value"
                ],
                "type": "column"
              }
            ]
          ],
          "timeColumn": "time",
          "where": [
            {
              "name": "$__timeFilter",
              "params": [],
              "type": "macro"
            }
          ]
        },
        {
          "format": "time_series",
          "group": [],
          "metricColumn": "none",
          "rawQuery": true,
          "rawSql": "SELECT sh.ts as time, (SELECT (result->'aggs'->'speed'->'value')::INTEGER FROM fact_history_v1 WHERE id = 3 AND ts = (sh.facts_ids->>'3')::timestamptZ) as speed_montpellier FROM situation_history_v1 as sh\nWHERE\n  $__timeFilter(sh.ts)\nORDER BY sh.ts",
          "refId": "D",
          "select": [
            [
              {
                "params": [
                  "value"
                ],
                "type": "column"
              }
            ]
          ],
          "timeColumn": "time",
          "where": [
            {
              "name": "$__timeFilter",
              "params": [],
              "type": "macro"
            }
          ]
        }
      ],
      "thresholds": [],
      "timeFrom": null,
      "timeRegions": [],
      "timeShift": null,
      "title": "Wind Speed",
      "tooltip": {
        "shared": true,
        "sort": 0,
        "value_type": "individual"
      },
      "type": "graph",
      "xaxis": {
        "buckets": null,
        "mode": "time",
        "name": null,
        "show": true,
        "values": []
      },
      "yaxes": [
        {
          "format": "short",
          "label": null,
          "logBase": 1,
          "max": null,
          "min": null,
          "show": true
        },
        {
          "format": "short",
          "label": null,
          "logBase": 1,
          "max": null,
          "min": null,
          "show": true
        }
      ],
      "yaxis": {
        "align": false,
        "alignLevel": null
      }
    }
  ],
  "refresh": "5s",
  "schemaVersion": 26,
  "style": "dark",
  "tags": [],
  "templating": {
    "list": []
  },
  "time": {
    "from": "now-1h",
    "to": "now"
  },
  "timepicker": {},
  "timezone": "",
  "title": "Wind Speed",
  "uid": "UuBppLTGz",
  "version": 4
}
